{
  "DEFAULT":
  {
    "file_path": "E:/University of Bremen MSc/masters_thesis/IAT_sebastian/dataset_26_april_3.csv",
    "file_path_ubuntu":"/home/atif/20_aug_1.csv",
    "file_path_ubuntu_1":"/home/atif/dataset_26_april_3.csv",
    "feb_march_file":"/home/atif/feb_march_1.csv",
      
    "file_path_server_feb_march":"/home/atif/feb_march_1.csv",
    "file_path_server_april_may":"/home/atif/april_may_1.csv",
    "file_path_server_june_july":"/home/atif/june_july_1.csv",


    "file_ubuntu_feb_march": "/media/atif/0820209220208930/ms_thesis/sliced_dataframe/feb_march_1.csv",
    "file_ubuntu_april_may": "/media/atif/0820209220208930/ms_thesis/sliced_dataframe/april_may_1.csv",
    "file_ubuntu_june_july": "/media/atif/0820209220208930/ms_thesis/sliced_dataframe/june_july_1.csv",

    "file_windows_feb_march": "F:/ms_thesis/sliced_dataframe/feb_march_1.csv",
    "file_windows_april_may": "F:/ms_thesis/sliced_dataframe/april_may_1.csv",
    "file_windows_june_july": "F:/ms_thesis/sliced_dataframe/june_july_1.csv",

    "start_point_dataframe": 0,
    "end_point_dataframe": 25000,
    "date_column": "dateTime",
    "target_column" : "AEWIHO_T9AV2",
    "req_drop_value_target":0,
    "blast_furnace_signal_b" : "DEWIHOBT9_I0",
    "req_value_of_blast_furnace_B":100,
    "blast_furnace_signal_a" : "DEWIHOAT9_I0",
    "req_value_of_blast_furnace_A":98,
    "max_best_number": 20,
    "correlation_threshold_min_value": 0.6,
    "correlation_threshold_max_value": 0.9,
    "image_type": ".jpg",
    "subfolder_feature_vs_target": "feature_vs_target",
    "evaluation_metrics_file": "evaluation_metrics.txt",
    "required_number_of_test_data": 1000,
    "n_steps_lstm" : 2,
    "epochs": 30,
    "batch_size": 32
  }
}
